p100test1/__init__.py
p100test1/funciones.py
p100test1-0.0.1.dist-info/METADATA
p100test1-0.0.1.dist-info/WHEEL
p100test1-0.0.1.dist-info/top_level.txt
p100test1-0.0.1.dist-info/RECORD
