Metadata-Version: 2.1
Name: p100test1
Version: 0.0.1
Summary: Librería para la practica 1
Home-page: UNKNOWN
Author: Erdana
Author-email: UNKNOWN
License: MIT
Platform: UNKNOWN
Requires-Dist: numpy
